data/gdim.columns.json
data/isocodes.csv
openborders/__init__.py
openborders/cli.py
openborders/data.py
openborders/indices.py
openborders/utils.py
openborders-0.1.2.dist-info/entry_points.txt
openborders-0.1.2.dist-info/METADATA
openborders-0.1.2.dist-info/WHEEL
openborders-0.1.2.dist-info/RECORD
