Metadata-Version: 2.1
Name: openborders
Version: 0.1.2
Summary: 
Home-page: https://arnos-stuff.github.io/open-borders-index
Author: arnos-stuff
Author-email: mail@arnov.dev
Requires-Python: >=3.11,<4.0
Classifier: Programming Language :: Python :: 3
Classifier: Programming Language :: Python :: 3.11
Provides-Extra: draw
Requires-Dist: ipywidgets (>=8.0.6,<9.0.0) ; extra == "draw"
Requires-Dist: mkdocs-coverage (>=0.2.7,<0.3.0)
Requires-Dist: numpy (>=1.25.0,<2.0.0)
Requires-Dist: openpyxl (>=3.1.2,<4.0.0)
Requires-Dist: pandas (>=2.0.2,<3.0.0)
Requires-Dist: plotly (>=5.15.0,<6.0.0) ; extra == "draw"
Requires-Dist: shiny (>=0.3.3,<0.4.0) ; extra == "draw"
Requires-Dist: shinyswatch (>=0.2.4,<0.3.0) ; extra == "draw"
Requires-Dist: shinywidgets (>=0.2.1,<0.3.0) ; extra == "draw"
Requires-Dist: typer-tinydb (>=0.1.4,<0.2.0)
Requires-Dist: wbdata (>=0.3.0,<0.4.0)
